channels.py
sendonemail.py
sendonteams.py
sendnotifications-2025.4.2.dist-info/licenses/LICENSE
sendnotifications-2025.4.2.dist-info/METADATA
sendnotifications-2025.4.2.dist-info/WHEEL
sendnotifications-2025.4.2.dist-info/top_level.txt
sendnotifications-2025.4.2.dist-info/RECORD
