Metadata-Version: 2.4
Name: sendnotifications
Version: 2025.4.2
Summary: Send Notifications to MSTeams or Email via sns!
Author-email: Vara Thelu <vthelu@costar.com>
Maintainer-email: Vara Thelu <vthelu@costar.com>
License-Expression: MIT
Project-URL: Homepage, https://example.com
Project-URL: Documentation, https://readthedocs.org
Project-URL: Repository, https://github.com/me/spam.git
Project-URL: Bug Tracker, https://github.com/me/spam/issues
Project-URL: Changelog, https://github.com/me/spam/blob/master/CHANGELOG.md
Keywords: sendnotifications,NotifyMSTeams,NotifyEmail
Classifier: Development Status :: 4 - Beta
Classifier: Programming Language :: Python
Requires-Python: >=3.10
License-File: LICENSE
Requires-Dist: urllib3
Dynamic: license-file
